MANIFEST.in
README.md
setup.py
orbital_sim.egg-info/PKG-INFO
orbital_sim.egg-info/SOURCES.txt
orbital_sim.egg-info/dependency_links.txt
orbital_sim.egg-info/requires.txt
orbital_sim.egg-info/top_level.txt
orbitalsim/__init__.py
orbitalsim/entities.py
orbitalsim/environment.py
orbitalsim/presets.py
orbitalsim/simulation.py
orbitalsim/fonts/Inconsolata.ttf