Metadata-Version: 2.1
Name: orbital-sim
Version: 0.9.2
Summary: A simple physics engine build over a PyGame simulation to model planetary orbits in space
Home-page: https://github.com/jasonfyw/orbital-sim
Author: Jason Wang
Author-email: jasonwang0610@gmail.com
License: MIT
Download-URL: https://github.com/jasonfyw/orbital-sim/archive/v0.9.2.tar.gz
Platform: UNKNOWN
Classifier: License :: OSI Approved :: MIT License
Classifier: Programming Language :: Python :: 3
Classifier: Programming Language :: Python :: 3.7
